Metadata-Version: 2.1
Name: scrapy-zenscrape
Version: 0.0.3
Summary: Scrapy middleware for Zenscrape
Home-page: https://github.com/saasindustries/scrapy-zenscrape
Author: Clemens Ehrenreich
Maintainer: Andreas Altheimer
Maintainer-email: office@zenscrape.com
License: MIT
Platform: UNKNOWN
Classifier: License :: OSI Approved :: MIT License
Classifier: Programming Language :: Python
Classifier: Programming Language :: Python :: 3
Classifier: Programming Language :: Python :: 3.5
Classifier: Programming Language :: Python :: 3.6
Classifier: Framework :: Scrapy
Classifier: Topic :: Software Development :: Libraries :: Application Frameworks
Classifier: Topic :: Software Development :: Libraries :: Python Modules
Requires-Python: >=3.5
